exmail/__init__.py
exmail/client/__init__.py
exmail/client/base.py
exmail/client/api/__init__.py
exmail/client/api/base.py
exmail/client/api/department.py
exmail/client/api/group.py
exmail/client/api/log.py
exmail/client/api/mail.py
exmail/client/api/option.py
exmail/client/api/service.py
exmail/client/api/tag.py
exmail/client/api/user.py
exmail/core/__init__.py
exmail/core/exceptions.py
exmail/core/utils.py
exmail/storage/__init__.py
exmail/storage/cache.py
exmail/storage/kvstorage.py
exmail/storage/memorystorage.py
exmail_sdk-1.0.0.dist-info/LICENSE
exmail_sdk-1.0.0.dist-info/METADATA
exmail_sdk-1.0.0.dist-info/WHEEL
exmail_sdk-1.0.0.dist-info/top_level.txt
exmail_sdk-1.0.0.dist-info/RECORD
